hlpl_english_words/__init__.py
hlpl_english_words/__main__.py
hlpl_english_words/english_words.py
hlpl_english_words/hlpl_english_words.db
hlpl_english_words/setup.cfg
hlpl_english_words-1.0.0.dist-info/LICENSE
hlpl_english_words-1.0.0.dist-info/METADATA
hlpl_english_words-1.0.0.dist-info/WHEEL
hlpl_english_words-1.0.0.dist-info/entry_points.txt
hlpl_english_words-1.0.0.dist-info/top_level.txt
hlpl_english_words-1.0.0.dist-info/RECORD
