Metadata-Version: 2.1
Name: hlpl-english-words
Version: 1.0.0
Summary: hlpl english words list (or english words database)
Home-page: https://hlpl.net/resources
Author: Ahmida Bendjoudi
Author-email: email@hlpl.net
License: MIT
Download-URL: https://hlpl.net/resources/download/
Project-URL: hlpl, https://hlpl.net
Project-URL: hlpl_english_words-docs, https://docs.hlpl.net
Project-URL: hlpl_english_words-forum, https://hlpl.net/hlpl-forums
Project-URL: hlpl_english_words-github, https://github.com/hlpl/english-words
Keywords: hlpl_english_words,hlpl english words,english words,hlpl english words,hlpl
Platform: UNKNOWN
Classifier: Natural Language :: English
Requires-Python: >=3, <=3.9
